Metadata-Version: 2.1
Name: codedepth
Version: 3.0.0
Summary: Generates scores for how many layers of local imports/exports are in a file
Home-page: https://github.com/immijimmi/codedepth
Download-URL: https://github.com/immijimmi/codedepth/archive/refs/tags/v3.0.0.tar.gz
Author: immijimmi
Author-email: immijimmi1@gmail.com
License: MIT
Keywords: abstraction,level,directory,abstract,imports,import
Classifier: Development Status :: 4 - Beta
Classifier: Environment :: Console
Classifier: Intended Audience :: Developers
Classifier: Topic :: Software Development :: Documentation
Classifier: License :: OSI Approved :: MIT License
Classifier: Programming Language :: Python :: 3.8
License-File: LICENSE.txt
Requires-Dist: graphviz~=0.16
Requires-Dist: networkx~=2.5
